framework_m/__init__.py
framework_m/py.typed
framework_m/adapters/__init__.py
framework_m/adapters/factory.py
framework_m/adapters/tenant.py
framework_m/adapters/audit/__init__.py
framework_m/adapters/audit/database_audit.py
framework_m/adapters/audit/file_audit.py
framework_m/adapters/auth/__init__.py
framework_m/adapters/auth/citadel_policy.py
framework_m/adapters/auth/federated_identity.py
framework_m/adapters/auth/local_identity.py
framework_m/adapters/auth/rbac_permission.py
framework_m/adapters/auth/session_store.py
framework_m/adapters/auth/strategies.py
framework_m/adapters/cache/__init__.py
framework_m/adapters/cache/redis_cache.py
framework_m/adapters/db/__init__.py
framework_m/adapters/db/connection.py
framework_m/adapters/db/field_registry.py
framework_m/adapters/db/generic_repository.py
framework_m/adapters/db/migration.py
framework_m/adapters/db/outbox_repository.py
framework_m/adapters/db/repository_factory.py
framework_m/adapters/db/schema_mapper.py
framework_m/adapters/db/session.py
framework_m/adapters/db/table_registry.py
framework_m/adapters/email/__init__.py
framework_m/adapters/email/processor.py
framework_m/adapters/email/queue_adapter.py
framework_m/adapters/email/sender_adapter.py
framework_m/adapters/events/__init__.py
framework_m/adapters/events/inmemory_event_bus.py
framework_m/adapters/events/nats_event_bus.py
framework_m/adapters/i18n/__init__.py
framework_m/adapters/jobs/__init__.py
framework_m/adapters/jobs/job_logger.py
framework_m/adapters/jobs/outbox_worker.py
framework_m/adapters/jobs/schedules.py
framework_m/adapters/jobs/taskiq_adapter.py
framework_m/adapters/print/__init__.py
framework_m/adapters/print/gotenberg_adapter.py
framework_m/adapters/print/jinja_adapter.py
framework_m/adapters/socket/__init__.py
framework_m/adapters/socket/nats_socket.py
framework_m/adapters/storage/__init__.py
framework_m/adapters/storage/local.py
framework_m/adapters/storage/memory.py
framework_m/adapters/storage/s3.py
framework_m-0.2.5.dist-info/METADATA
framework_m-0.2.5.dist-info/WHEEL
framework_m-0.2.5.dist-info/entry_points.txt
framework_m-0.2.5.dist-info/RECORD
