Metadata-Version: 2.4
Name: framework-m
Version: 0.2.5
Summary: A modern, metadata-driven business application framework
Project-URL: Homepage, https://gitlab.com/castlecraft/framework-m
Project-URL: Documentation, https://gitlab.com/castlecraft/framework-m#readme
Project-URL: Repository, https://gitlab.com/castlecraft/framework-m
Author: Framework M Contributors
License: MIT
Keywords: async,business,doctype,framework,metadata
Classifier: Development Status :: 3 - Alpha
Classifier: Framework :: AsyncIO
Classifier: Intended Audience :: Developers
Classifier: License :: OSI Approved :: MIT License
Classifier: Programming Language :: Python :: 3
Classifier: Programming Language :: Python :: 3.12
Classifier: Programming Language :: Python :: 3.13
Classifier: Typing :: Typed
Requires-Python: >=3.12
Requires-Dist: aioboto3>=15.5.0
Requires-Dist: aiofiles>=25.1.0
Requires-Dist: alembic>=1.13.0
Requires-Dist: argon2-cffi>=23.1.0
Requires-Dist: asyncpg>=0.29.0
Requires-Dist: boto3-stubs>=1.42.21
Requires-Dist: botocore-stubs>=1.42.21
Requires-Dist: cyclopts>=3.0.0
Requires-Dist: dependency-injector>=4.41.0
Requires-Dist: litestar[standard]>=2.0.0
Requires-Dist: nats-py>=2.0.0
Requires-Dist: pydantic-settings>=2.0.0
Requires-Dist: pydantic>=2.0.0
Requires-Dist: pyjwt>=2.8.0
Requires-Dist: redis>=5.0.0
Requires-Dist: sqlalchemy[asyncio]>=2.0.0
Requires-Dist: taskiq-nats>=0.4.0
Requires-Dist: taskiq>=0.11.0
Requires-Dist: types-aiobotocore>=3.1.0
